the_pitch/__init__.py
the_pitch/caches/__init__.py
the_pitch/caches/cache.py
the_pitch/conditions/__init__.py
the_pitch/conditions/factory.py
the_pitch/converters/__init__.py
the_pitch/converters/utils.py
the_pitch/data/__init__.py
the_pitch/data/query.py
the_pitch/domain/__init__.py
the_pitch/domain/condition.py
the_pitch/domain/entry_settings.py
the_pitch/domain/enums.py
the_pitch/domain/order_target.py
the_pitch/domain/pitch.py
the_pitch/domain/portfolio.py
the_pitch/domain/position.py
the_pitch/domain/rule.py
the_pitch/domain/rule_value.py
the_pitch/domain/simulation_dataset.py
the_pitch/domain/stock_price.py
the_pitch/domain/strategy.py
the_pitch/domain/strategy_payload.py
the_pitch/engines/__init__.py
the_pitch/engines/pitch_engine.py
the_pitch/engines/portfolio_wrapper.py
the_pitch/indicators/__init__.py
the_pitch/indicators/abstract_indicator.py
the_pitch/indicators/atr.py
the_pitch/indicators/bollinger_bands.py
the_pitch/indicators/difference.py
the_pitch/indicators/ema.py
the_pitch/indicators/gap.py
the_pitch/indicators/macd.py
the_pitch/indicators/percent_less.py
the_pitch/indicators/percent_more.py
the_pitch/indicators/roc.py
the_pitch/indicators/rsi.py
the_pitch/indicators/sma.py
the_pitch/logging/__init__.py
the_pitch/logging/abstract_logger.py
the_pitch/logging/file.py
the_pitch/logging/slack.py
the_pitch/management/__init__.py
the_pitch/management/risk.py
the_pitch/managers/__init__.py
the_pitch/managers/chart_manager.py
the_pitch/managers/portfolio_managers.py
the_pitch/repositories/__init__.py
the_pitch/repositories/stock_frame.py
the_pitch/simulators/__init__.py
the_pitch/simulators/pitch_simulator.py
the_pitch/simulators/scorer.py
the_pitch/strategies/__init__.py
the_pitch/strategies/factory.py
the_pitch-0.0.1.7.dist-info/LICENSE
the_pitch-0.0.1.7.dist-info/METADATA
the_pitch-0.0.1.7.dist-info/WHEEL
the_pitch-0.0.1.7.dist-info/top_level.txt
the_pitch-0.0.1.7.dist-info/RECORD
