Metadata-Version: 2.1
Name: the-pitch
Version: 0.0.1.7
Summary: UNKNOWN
Home-page: UNKNOWN
Author: UNKNOWN
Author-email: UNKNOWN
License: UNKNOWN
Platform: UNKNOWN
Requires-Dist: pytest
Requires-Dist: pandas
Requires-Dist: numpy
Requires-Dist: pandas-datareader
Requires-Dist: pandas-ta
